cinchdb/__init__.py
cinchdb/__main__.py
cinchdb/config.py
cinchdb/cli/__init__.py
cinchdb/cli/main.py
cinchdb/cli/utils.py
cinchdb/cli/commands/__init__.py
cinchdb/cli/commands/branch.py
cinchdb/cli/commands/codegen.py
cinchdb/cli/commands/column.py
cinchdb/cli/commands/data.py
cinchdb/cli/commands/database.py
cinchdb/cli/commands/index.py
cinchdb/cli/commands/query.py
cinchdb/cli/commands/remote.py
cinchdb/cli/commands/table.py
cinchdb/cli/commands/tenant.py
cinchdb/cli/commands/view.py
cinchdb/cli/handlers/__init__.py
cinchdb/cli/handlers/codegen_handler.py
cinchdb/core/__init__.py
cinchdb/core/connection.py
cinchdb/core/database.py
cinchdb/core/initializer.py
cinchdb/core/maintenance_utils.py
cinchdb/core/path_utils.py
cinchdb/core/tenant_activation.py
cinchdb/infrastructure/metadata_connection_pool.py
cinchdb/infrastructure/metadata_db.py
cinchdb/managers/__init__.py
cinchdb/managers/base.py
cinchdb/managers/branch.py
cinchdb/managers/change_applier.py
cinchdb/managers/change_comparator.py
cinchdb/managers/change_tracker.py
cinchdb/managers/codegen.py
cinchdb/managers/column.py
cinchdb/managers/data.py
cinchdb/managers/index.py
cinchdb/managers/kv.py
cinchdb/managers/merge_manager.py
cinchdb/managers/query.py
cinchdb/managers/table.py
cinchdb/managers/tenant.py
cinchdb/managers/view.py
cinchdb/models/__init__.py
cinchdb/models/base.py
cinchdb/models/branch.py
cinchdb/models/change.py
cinchdb/models/database.py
cinchdb/models/project.py
cinchdb/models/schema_snapshot.py
cinchdb/models/table.py
cinchdb/models/tenant.py
cinchdb/models/view.py
cinchdb/plugins/__init__.py
cinchdb/plugins/base.py
cinchdb/plugins/decorators.py
cinchdb/plugins/manager.py
cinchdb/utils/__init__.py
cinchdb/utils/name_validator.py
cinchdb/utils/sql_validator.py
cinchdb/utils/type_utils.py
cinchdb-0.1.24.dist-info/METADATA
cinchdb-0.1.24.dist-info/WHEEL
cinchdb-0.1.24.dist-info/entry_points.txt
cinchdb-0.1.24.dist-info/licenses/LICENSE
cinchdb-0.1.24.dist-info/RECORD
