Metadata-Version: 2.4
Name: cinchdb
Version: 0.1.24
Summary: A Git-like SQLite database management system with branching and multi-tenancy
Project-URL: Homepage, https://github.com/russellromney/cinchdb
Project-URL: Documentation, https://russellromney.github.io/cinchdb
Project-URL: Repository, https://github.com/russellromney/cinchdb
Project-URL: Issues, https://github.com/russellromney/cinchdb/issues
Author: Russell Romney
License: MIT
License-File: LICENSE
Keywords: branching,database,git,multi-tenant,sqlite
Classifier: Development Status :: 3 - Alpha
Classifier: Intended Audience :: Developers
Classifier: License :: OSI Approved :: MIT License
Classifier: Programming Language :: Python :: 3
Classifier: Programming Language :: Python :: 3.10
Classifier: Programming Language :: Python :: 3.11
Classifier: Programming Language :: Python :: 3.12
Requires-Python: >=3.10
Requires-Dist: httpx>=0.25.0
Requires-Dist: psutil>=7.0.0
Requires-Dist: pydantic>=2.0.0
Requires-Dist: requests>=2.28.0
Requires-Dist: rich>=13.0.0
Requires-Dist: toml>=0.10.0
Requires-Dist: typer>=0.9.0
Provides-Extra: encryption
Requires-Dist: pysqlcipher3>=1.2.0; extra == 'encryption'
